encryptos/__init__.py
encryptos/en.py
encryptos/version.py
encryptos-1.0.1.dist-info/LICENSE
encryptos-1.0.1.dist-info/METADATA
encryptos-1.0.1.dist-info/WHEEL
encryptos-1.0.1.dist-info/top_level.txt
encryptos-1.0.1.dist-info/RECORD
