Metadata-Version: 2.1
Name: encryptos
Version: 1.0.1
Summary: A simple module to encrypt and decrypt data using a secret keys/passcodes
Author-email: Brian Musakwa <digreatbrian@gmail.com>
Project-URL: Homepage, https://github.com/digreatbrian/encryptos
Project-URL: Bug Tracker, https://github.com/digreatbrian/encryptos/issues
Keywords: encrypt,encryptos,encrypto,decrypt,lock,data,encryption,secure,aes
Classifier: Programming Language :: Python :: 3
Classifier: License :: OSI Approved :: GNU Lesser General Public License v2 (LGPLv2)
Classifier: Operating System :: OS Independent
Requires-Python: >=3.7
License-File: LICENSE
